nvselector/__init__.py
nvselector/selector.py
nvselector-0.0.1.dist-info/LICENSE
nvselector-0.0.1.dist-info/METADATA
nvselector-0.0.1.dist-info/WHEEL
nvselector-0.0.1.dist-info/top_level.txt
nvselector-0.0.1.dist-info/RECORD
