Metadata-Version: 2.1
Name: nvselector
Version: 0.0.1
Summary: Auto selector for NVIDIA GPUs
Home-page: https://github.com/yuanmu97/nvselector
Author: yuanmu
Author-email: ym0813@mail.ustc.edu.cn
License: UNKNOWN
Platform: UNKNOWN
Requires-Dist: pynvml
